aiomarine/__init__.py
aiomarine-0.1.0.dist-info/LICENSE
aiomarine-0.1.0.dist-info/METADATA
aiomarine-0.1.0.dist-info/WHEEL
aiomarine-0.1.0.dist-info/RECORD
