Metadata-Version: 2.1
Name: aiomarine
Version: 0.1.0
Summary: 
License: MIT
Author: Alexeev Bronislav
Author-email: alexeev.dev@mail.ru
Requires-Python: >=3.11,<4.0
Classifier: License :: OSI Approved :: MIT License
Classifier: Programming Language :: Python :: 3
Classifier: Programming Language :: Python :: 3.11
Classifier: Programming Language :: Python :: 3.12
Classifier: Programming Language :: Python :: 3.13
Requires-Dist: aiosqlite (>=0.21.0,<0.22.0)
Requires-Dist: asyncio (>=3.4.3,<4.0.0)
Requires-Dist: orjson (>=3.10.16,<4.0.0)
Requires-Dist: rich (>=14.0.0,<15.0.0)
